tokre/__init__.py
tokre/core/macros.py
tokre/core/matchers.py
tokre/core/parsing.py
tokre/core/prediction_primitives.py
tokre/core/synth_feat.py
tokre/core/tree_to_matcher.py
tokre/labelling/__init__.py
tokre/labelling/create_label.py
tokre/labelling/get_words.py
tokre/labelling/literal_set_utils.py
tokre/labelling/query_openai.py
tokre/setup.py
tokre/utils.py
tokre-1.6.0.post3.dist-info/METADATA
tokre-1.6.0.post3.dist-info/WHEEL
tokre-1.6.0.post3.dist-info/RECORD
