Metadata-Version: 2.1
Name: tokre
Version: 1.6.0.post3
Summary: 
Author: Noa Nabeshima
Author-email: noanabeshima@gmail.com
Requires-Python: >=3.11,<4.0
Classifier: Programming Language :: Python :: 3
Classifier: Programming Language :: Python :: 3.11
Classifier: Programming Language :: Python :: 3.12
Requires-Dist: backoff (>=2.2.1,<3.0.0)
Requires-Dist: black (>=24.4.2,<25.0.0)
Requires-Dist: frozendict (>=2.4.4,<3.0.0)
Requires-Dist: lark (>=1.1.9,<2.0.0)
Requires-Dist: numpy (>=1.24.0,<2.0.0)
Requires-Dist: openai (>=1.37.1,<2.0.0)
Requires-Dist: pathlib (>=1.0.1,<2.0.0)
Requires-Dist: regex (>=2024.7.24,<2025.0.0)
Requires-Dist: schedulefree (>=1.4,<2.0)
Requires-Dist: tqdm (>=4.66.4,<5.0.0)
Requires-Dist: transformers (>=4.48.1,<5.0.0)
